tedeous/__init__.py
tedeous/config.py
tedeous/data.py
tedeous/data_CSG.py
tedeous/derivative.py
tedeous/device.py
tedeous/eval.py
tedeous/finite_diffs.py
tedeous/input_preprocessing.py
tedeous/losses.py
tedeous/model.py
tedeous/models.py
tedeous/points_type.py
tedeous/solution.py
tedeous/utils.py
tedeous/version.py
tedeous/callbacks/__init__.py
tedeous/callbacks/adaptive_lambda.py
tedeous/callbacks/cache.py
tedeous/callbacks/callback.py
tedeous/callbacks/callback_list.py
tedeous/callbacks/early_stopping.py
tedeous/callbacks/inverse_task.py
tedeous/callbacks/plot.py
tedeous/callbacks/save_model.py
tedeous/optimizers/CSO.py
tedeous/optimizers/__init__.py
tedeous/optimizers/closure.py
tedeous/optimizers/ngd.py
tedeous/optimizers/nys_newton_cg.py
tedeous/optimizers/optimizer.py
tedeous/optimizers/pso.py
tedeous-0.4.11.dist-info/licenses/LICENCE
tedeous-0.4.11.dist-info/METADATA
tedeous-0.4.11.dist-info/WHEEL
tedeous-0.4.11.dist-info/top_level.txt
tedeous-0.4.11.dist-info/RECORD
