Metadata-Version: 2.4
Name: TEDEouS
Version: 0.4.11
Summary: TEDEouS - Torch Exhaustive Differential Equations Solver. Differential equation solver, based on pytorch library
Home-page: https://github.com/ITMO-NSS-team/torch_DE_solver
Author: AH and NSS Lab
Author-email: itmo.nss.team@gmail.com
License: MIT License
Classifier: Development Status :: 3 - Alpha
Classifier: Programming Language :: Python :: 3
Classifier: License :: OSI Approved :: MIT License
Classifier: Operating System :: OS Independent
Classifier: Programming Language :: Python :: 3.8
Classifier: Programming Language :: Python :: 3.9
Classifier: Programming Language :: Python :: 3.10
Requires-Python: >=3.8
License-File: LICENCE
Requires-Dist: matplotlib
Requires-Dist: numpy
Requires-Dist: pandas
Requires-Dist: scipy
Requires-Dist: seaborn
Requires-Dist: torch>=2.0
Requires-Dist: autodocsumm
Requires-Dist: typing
Requires-Dist: SALib
Dynamic: author
Dynamic: author-email
Dynamic: classifier
Dynamic: description
Dynamic: description-content-type
Dynamic: home-page
Dynamic: license
Dynamic: license-file
Dynamic: requires-dist
Dynamic: requires-python
Dynamic: summary
